{
  "schema_version": "0.1.0",
  "component": "MegaMenu/Item",
  "status": "component-contract-backed-generic-primitive",
  "source": {
    "storybook_title": "Components/MegaMenu/Item",
    "storybook_index": "../../../../research/storybook/index.json",
    "component_contract": "design-system-plugin/design-system/contracts/components/mega-menu-item.contract.json"
  },
  "supported_primitives": [
    {
      "id": "mega-menu-item",
      "data_attribute": "data-primitive=\"mega-menu-item\"",
      "required_semantics": [
        "component package sample",
        "source-provenance markers"
      ]
    }
  ],
  "story_contract": {
    "required_attribute": "data-story-id",
    "known_story_ids": [
      "components-megamenu-item--default"
    ]
  },
  "source_provenance": {
    "docs_id": "components-megamenu-item--docs",
    "component_contract": "design-system-plugin/design-system/contracts/components/mega-menu-item.contract.json",
    "token_source": "foundations-colors--docs"
  }
}
